CXAI/CXAI_CAM.py
CXAI/CXAI_config.py
CXAI/CXAI_dataloader.py
CXAI/CXAI_evaluation.py
CXAI/CXAI_model_training.py
CXAI/__init__.py
Cardiac_eXplainableAI_CXAI-0.0.3.dist-info/LICENSE
Cardiac_eXplainableAI_CXAI-0.0.3.dist-info/METADATA
Cardiac_eXplainableAI_CXAI-0.0.3.dist-info/WHEEL
Cardiac_eXplainableAI_CXAI-0.0.3.dist-info/top_level.txt
Cardiac_eXplainableAI_CXAI-0.0.3.dist-info/RECORD
