Metadata-Version: 2.1
Name: Cardiac-eXplainableAI-CXAI
Version: 0.0.3
Summary: This package provides a framework that uses the ACDC data to train multiple CNN models and create GradCAMs of the resulting data.
Home-page: https://gitlab.com/plumdeq/alessa-master-thesis-mura
Author: Alessa Stria
Author-email: alessa.stria@gmail.com
License: UNKNOWN
Project-URL: Bug Tracker, https://gitlab.com/plumdeq/alessa-master-thesis-mura/-/issues
Platform: UNKNOWN
Classifier: Programming Language :: Python :: 3
Classifier: License :: OSI Approved :: Apache Software License
Classifier: Operating System :: OS Independent
Requires-Python: >=3.6
License-File: LICENSE
